print_merge_generator-1.0.0.dist-info/METADATA
print_merge_generator-1.0.0.dist-info/WHEEL
print_merge_generator-1.0.0.dist-info/licenses/LICENSE
print_merge_generator.libs/libgcc_s-b5472b99.so.1
print_merge_generator/__init__.py
print_merge_generator/print_merge_generator.pypy311-pp73-x86-linux-gnu.so
print_merge_generator-1.0.0.dist-info/RECORD
