Metadata-Version: 2.4
Name: print_merge_generator
Version: 1.0.0
Classifier: Programming Language :: Rust
Classifier: Programming Language :: Python :: Implementation :: CPython
Classifier: Programming Language :: Python :: Implementation :: PyPy
License-File: LICENSE
Summary: Bindings for PrintMergeGenerator's Rust backend
Requires-Python: >=3.10
